tests/__init__.py
tests/test_validate.py
tests/test_validator.py
tests/test_validator_error.py
tests/test_validator_path.py
tests/test_validator_return.py
tests/validators/__init__.py
tests/validators/test_dict_validator.py
tests/validators/test_email_validator.py
tests/validators/test_enum_validator.py
tests/validators/test_float_validator.py
tests/validators/test_integer_validator.py
tests/validators/test_list_validator.py
tests/validators/test_nullable_validator.py
tests/validators/test_numeric_validator.py
tests/validators/test_string_validator.py
wvalidate/__init__.py
wvalidate/validate.py
wvalidate/validator.py
wvalidate/validator_error.py
wvalidate/validator_path.py
wvalidate/validator_return.py
wvalidate/validators/__init__.py
wvalidate/validators/dict_validator.py
wvalidate/validators/email_validator.py
wvalidate/validators/enum_validator.py
wvalidate/validators/float_validator.py
wvalidate/validators/integer_validator.py
wvalidate/validators/list_validator.py
wvalidate/validators/nullable_validator.py
wvalidate/validators/numeric_validator.py
wvalidate/validators/string_validator.py
wvalidate-0.0.1.dist-info/LICENSE
wvalidate-0.0.1.dist-info/METADATA
wvalidate-0.0.1.dist-info/WHEEL
wvalidate-0.0.1.dist-info/top_level.txt
wvalidate-0.0.1.dist-info/RECORD
