Metadata-Version: 2.1
Name: wvalidate
Version: 0.0.1
Summary: Simple data structure validator
Home-page: UNKNOWN
Author: Leandro Crispim
Author-email: leandro.c25@aluno.ifsc.edu.br
License: MIT License
Keywords: validator
Platform: UNKNOWN
